LICENSE
MANIFEST.in
README.rst
buildout.cfg
develop.cfg
requirements.txt
setup.py
version.txt
bob/__init__.py
bob.db.putvein.egg-info/PKG-INFO
bob.db.putvein.egg-info/SOURCES.txt
bob.db.putvein.egg-info/dependency_links.txt
bob.db.putvein.egg-info/entry_points.txt
bob.db.putvein.egg-info/not-zip-safe
bob.db.putvein.egg-info/requires.txt
bob.db.putvein.egg-info/top_level.txt
bob/db/__init__.py
bob/db/putvein/__init__.py
bob/db/putvein/driver.py
bob/db/putvein/models.py
bob/db/putvein/query.py
bob/db/putvein/test.py
doc/conf.py
doc/guide.rst
doc/index.rst
doc/py_api.rst