Metadata-Version: 1.2
Name: bob.db.putvein
Version: 1.3.0
Summary: PUT Vein Database Access API for Bob
Home-page: http://gitlab.idiap.ch/bob/bob.db.putvein
Author: Philip Abbet
Author-email: philip.abbet@idiap.ch
Maintainer: Andre Anjos
Maintainer-email: andre.anjos@idiap.ch
License: BSD
Platform: UNKNOWN
Classifier: Framework :: Bob
Classifier: Development Status :: 4 - Beta
Classifier: Environment :: Console
Classifier: Intended Audience :: Developers
Classifier: Intended Audience :: Education
Classifier: Intended Audience :: Science/Research
Classifier: License :: OSI Approved :: BSD License
Classifier: Natural Language :: English
Classifier: Programming Language :: Python
Classifier: Programming Language :: Python :: 3
Classifier: Topic :: Scientific/Engineering :: Artificial Intelligence
Classifier: Topic :: Database :: Front-Ends
